pylinkwave/__init__.py
pylinkwave/__main__.py
pylinkwave/backoff.py
pylinkwave/enums.py
pylinkwave/exceptions.py
pylinkwave/filters.py
pylinkwave/lfu.py
pylinkwave/node.py
pylinkwave/payloads.py
pylinkwave/player.py
pylinkwave/py.typed
pylinkwave/queue.py
pylinkwave/tracks.py
pylinkwave/utils.py
pylinkwave/websocket.py
pylinkwave/types/__init__.py
pylinkwave/types/filters.py
pylinkwave/types/request.py
pylinkwave/types/response.py
pylinkwave/types/state.py
pylinkwave/types/stats.py
pylinkwave/types/tracks.py
pylinkwave/types/websocket.py
pylinkwave-3.4.1.dist-info/LICENSE
pylinkwave-3.4.1.dist-info/METADATA
pylinkwave-3.4.1.dist-info/WHEEL
pylinkwave-3.4.1.dist-info/top_level.txt
pylinkwave-3.4.1.dist-info/RECORD
